MANIFEST.in
README.md
requirements.txt
setup.py
LazyPyUtil.egg-info/PKG-INFO
LazyPyUtil.egg-info/SOURCES.txt
LazyPyUtil.egg-info/dependency_links.txt
LazyPyUtil.egg-info/requires.txt
LazyPyUtil.egg-info/top_level.txt
http_lib/__init__.py
http_lib/simple_http_client.py