Metadata-Version: 1.0
Name: LazyPyUtil
Version: 0.1.0
Summary: Woody's Lazy Python Utility
Home-page: https://github.com/ccy1219/LazyPyUtil
Author: Woody Chen
Author-email: ccy1219@gmail.com
License: MIT
Keywords: ccy1219,utility,library
Platform: any
